EasyDataPy/EasyDataPy.py
EasyDataPy/__init__.py
EasyDataPy-1.4.dist-info/METADATA
EasyDataPy-1.4.dist-info/WHEEL
EasyDataPy-1.4.dist-info/top_level.txt
EasyDataPy-1.4.dist-info/RECORD
