Metadata-Version: 2.1
Name: EasyDataPy
Version: 1.4
Summary: EasyDataPy through EasyData API key of State Bank of Pakistan helps to obtain information on and download a series of interest in Python for further analysis
Author: Dr. Syed Ateeb Akhter Shah
Author-email: syed.ateeb@wmich.edu
Keywords: EasyData,EasyDataPy
Classifier: Intended Audience :: Developers
Classifier: License :: OSI Approved :: MIT License
Classifier: Operating System :: OS Independent
Classifier: Programming Language :: Python
Requires-Dist: plotly
Requires-Dist: pandas
Requires-Dist: requests
Requires-Dist: readme-md
